git_pep8_commit_hook/__init__.py
git_pep8_commit_hook/__main__.py
git_pep8_commit_hook/commit_hook.py
git_pep8_commit_hook-0.1.0.dist-info/DESCRIPTION.rst
git_pep8_commit_hook-0.1.0.dist-info/entry_points.txt
git_pep8_commit_hook-0.1.0.dist-info/METADATA
git_pep8_commit_hook-0.1.0.dist-info/metadata.json
git_pep8_commit_hook-0.1.0.dist-info/RECORD
git_pep8_commit_hook-0.1.0.dist-info/top_level.txt
git_pep8_commit_hook-0.1.0.dist-info/WHEEL
