Metadata-Version: 2.0
Name: git-pep8-commit-hook
Version: 0.1.0
Summary: Git commit hook that checks Python files with pep8.
Home-page: https://github.com/sorenlind/git_pep8_commit_hook
Author: Soren Lind Kristiansen
Author-email: soren@gutsandglory.dk
License: Apache License, Version 2.0
Keywords: git commit pre-commit hook pep8 python
Platform: Any
Classifier: Development Status :: 3 - Alpha
Classifier: Environment :: Console
Classifier: License :: OSI Approved :: Apache Software License
Classifier: Operating System :: OS Independent
Classifier: Programming Language :: Python :: 2.7
Classifier: Programming Language :: Python :: 3
Requires-Dist: pep8
